{
  "competition_id": "italy-serie-a",
  "competition_name": "Serie A",
  "coverage": {
    "events": 647372,
    "matches": 380,
    "teams": 20
  },
  "era": "2017/18",
  "label": "Historical team research \u2014 never a live model input",
  "methods": {
    "chain_proxy": "consecutive same-team event run; a transparent proxy, not provider possession",
    "progressive_pass": "successful pass with normalized attacking x gain >= 20",
    "research_xt": "own 12x8 transition grid trained within this competition slice; positive completed-pass gains only"
  },
  "provenance": {
    "attribution": "Event data: Pappalardo et al., Scientific Data 6:236 (2019), CC BY 4.0 (collected by Wyscout).",
    "license": "CC-BY-4.0",
    "modifications": "Golavo aggregated raw events to competition-era team summaries; player identities and raw events are not redistributed.",
    "source_id": "pappalardo-wyscout-events"
  },
  "schema_version": "0.1.0",
  "status": "available",
  "team_scope": "team_aggregate_only",
  "teams": [
    {
      "chain_proxy_count": 14385,
      "chain_proxy_events": 35258,
      "goals_per_match": 1.5,
      "matches": 38,
      "pass_completion_pct": 83.8,
      "passes_attempted": 18632,
      "passes_completed": 15619,
      "progressive_chains_per_match": 95.87,
      "progressive_passes_per_match": 44.47,
      "research_xt_created_per_match": 2.35,
      "shots_per_match": 14.47,
      "team": "Atalanta",
      "team_id": 3172
    },
    {
      "chain_proxy_count": 12680,
      "chain_proxy_events": 31883,
      "goals_per_match": 0.84,
      "matches": 38,
      "pass_completion_pct": 83.6,
      "passes_attempted": 15673,
      "passes_completed": 13097,
      "progressive_chains_per_match": 90.5,
      "progressive_passes_per_match": 38.24,
      "research_xt_created_per_match": 1.648,
      "shots_per_match": 11.74,
      "team": "Benevento",
      "team_id": 3219
    },
    {
      "chain_proxy_count": 13479,
      "chain_proxy_events": 31347,
      "goals_per_match": 0.95,
      "matches": 38,
      "pass_completion_pct": 82.3,
      "passes_attempted": 15157,
      "passes_completed": 12467,
      "progressive_chains_per_match": 94.24,
      "progressive_passes_per_match": 41.63,
      "research_xt_created_per_match": 1.55,
      "shots_per_match": 8.74,
      "team": "Bologna",
      "team_id": 3166
    },
    {
      "chain_proxy_count": 13788,
      "chain_proxy_events": 30151,
      "goals_per_match": 0.87,
      "matches": 38,
      "pass_completion_pct": 78.8,
      "passes_attempted": 14094,
      "passes_completed": 11104,
      "progressive_chains_per_match": 95.5,
      "progressive_passes_per_match": 37.68,
      "research_xt_created_per_match": 1.872,
      "shots_per_match": 9.21,
      "team": "Cagliari",
      "team_id": 3173
    },
    {
      "chain_proxy_count": 13203,
      "chain_proxy_events": 30018,
      "goals_per_match": 0.95,
      "matches": 38,
      "pass_completion_pct": 80.5,
      "passes_attempted": 14516,
      "passes_completed": 11692,
      "progressive_chains_per_match": 96.58,
      "progressive_passes_per_match": 38.34,
      "research_xt_created_per_match": 1.76,
      "shots_per_match": 9.55,
      "team": "Chievo",
      "team_id": 3165
    },
    {
      "chain_proxy_count": 14244,
      "chain_proxy_events": 29679,
      "goals_per_match": 1.0,
      "matches": 38,
      "pass_completion_pct": 75.9,
      "passes_attempted": 12595,
      "passes_completed": 9556,
      "progressive_chains_per_match": 102.55,
      "progressive_passes_per_match": 37.13,
      "research_xt_created_per_match": 1.557,
      "shots_per_match": 9.97,
      "team": "Crotone",
      "team_id": 3197
    },
    {
      "chain_proxy_count": 13967,
      "chain_proxy_events": 33298,
      "goals_per_match": 1.39,
      "matches": 38,
      "pass_completion_pct": 83.5,
      "passes_attempted": 17148,
      "passes_completed": 14326,
      "progressive_chains_per_match": 92.79,
      "progressive_passes_per_match": 44.37,
      "research_xt_created_per_match": 2.247,
      "shots_per_match": 15.55,
      "team": "Fiorentina",
      "team_id": 3176
    },
    {
      "chain_proxy_count": 13555,
      "chain_proxy_events": 31444,
      "goals_per_match": 0.82,
      "matches": 38,
      "pass_completion_pct": 80.5,
      "passes_attempted": 15261,
      "passes_completed": 12289,
      "progressive_chains_per_match": 99.66,
      "progressive_passes_per_match": 42.08,
      "research_xt_created_per_match": 1.942,
      "shots_per_match": 10.45,
      "team": "Genoa",
      "team_id": 3193
    },
    {
      "chain_proxy_count": 13127,
      "chain_proxy_events": 29461,
      "goals_per_match": 0.79,
      "matches": 38,
      "pass_completion_pct": 79.1,
      "passes_attempted": 13397,
      "passes_completed": 10596,
      "progressive_chains_per_match": 95.89,
      "progressive_passes_per_match": 38.84,
      "research_xt_created_per_match": 1.381,
      "shots_per_match": 8.89,
      "team": "Hellas Verona",
      "team_id": 3194
    },
    {
      "chain_proxy_count": 12584,
      "chain_proxy_events": 34511,
      "goals_per_match": 1.68,
      "matches": 38,
      "pass_completion_pct": 85.8,
      "passes_attempted": 20450,
      "passes_completed": 17553,
      "progressive_chains_per_match": 82.76,
      "progressive_passes_per_match": 42.0,
      "research_xt_created_per_match": 2.421,
      "shots_per_match": 14.68,
      "team": "Internazionale",
      "team_id": 3161
    },
    {
      "chain_proxy_count": 12059,
      "chain_proxy_events": 34772,
      "goals_per_match": 2.16,
      "matches": 38,
      "pass_completion_pct": 88.4,
      "passes_attempted": 21519,
      "passes_completed": 19025,
      "progressive_chains_per_match": 73.58,
      "progressive_passes_per_match": 47.47,
      "research_xt_created_per_match": 2.225,
      "shots_per_match": 13.95,
      "team": "Juventus",
      "team_id": 3159
    },
    {
      "chain_proxy_count": 12852,
      "chain_proxy_events": 32829,
      "goals_per_match": 2.26,
      "matches": 38,
      "pass_completion_pct": 84.2,
      "passes_attempted": 18116,
      "passes_completed": 15245,
      "progressive_chains_per_match": 86.21,
      "progressive_passes_per_match": 47.26,
      "research_xt_created_per_match": 2.338,
      "shots_per_match": 14.08,
      "team": "Lazio",
      "team_id": 3162
    },
    {
      "chain_proxy_count": 12565,
      "chain_proxy_events": 33946,
      "goals_per_match": 1.42,
      "matches": 38,
      "pass_completion_pct": 86.3,
      "passes_attempted": 19484,
      "passes_completed": 16822,
      "progressive_chains_per_match": 84.37,
      "progressive_passes_per_match": 48.47,
      "research_xt_created_per_match": 2.42,
      "shots_per_match": 15.5,
      "team": "Milan",
      "team_id": 3157
    },
    {
      "chain_proxy_count": 12043,
      "chain_proxy_events": 39912,
      "goals_per_match": 1.87,
      "matches": 38,
      "pass_completion_pct": 88.2,
      "passes_attempted": 26874,
      "passes_completed": 23697,
      "progressive_chains_per_match": 79.74,
      "progressive_passes_per_match": 50.47,
      "research_xt_created_per_match": 2.593,
      "shots_per_match": 16.66,
      "team": "Napoli",
      "team_id": 3187
    },
    {
      "chain_proxy_count": 13123,
      "chain_proxy_events": 34013,
      "goals_per_match": 1.47,
      "matches": 38,
      "pass_completion_pct": 84.5,
      "passes_attempted": 19087,
      "passes_completed": 16127,
      "progressive_chains_per_match": 90.32,
      "progressive_passes_per_match": 48.24,
      "research_xt_created_per_match": 2.491,
      "shots_per_match": 16.63,
      "team": "Roma",
      "team_id": 3158
    },
    {
      "chain_proxy_count": 12969,
      "chain_proxy_events": 29677,
      "goals_per_match": 0.97,
      "matches": 38,
      "pass_completion_pct": 81.4,
      "passes_attempted": 13685,
      "passes_completed": 11145,
      "progressive_chains_per_match": 93.53,
      "progressive_passes_per_match": 36.24,
      "research_xt_created_per_match": 1.345,
      "shots_per_match": 9.53,
      "team": "SPAL",
      "team_id": 3204
    },
    {
      "chain_proxy_count": 13290,
      "chain_proxy_events": 33181,
      "goals_per_match": 1.47,
      "matches": 38,
      "pass_completion_pct": 84.5,
      "passes_attempted": 17833,
      "passes_completed": 15067,
      "progressive_chains_per_match": 90.68,
      "progressive_passes_per_match": 43.26,
      "research_xt_created_per_match": 2.008,
      "shots_per_match": 11.84,
      "team": "Sampdoria",
      "team_id": 3164
    },
    {
      "chain_proxy_count": 13643,
      "chain_proxy_events": 29519,
      "goals_per_match": 0.74,
      "matches": 38,
      "pass_completion_pct": 78.0,
      "passes_attempted": 13352,
      "passes_completed": 10420,
      "progressive_chains_per_match": 102.21,
      "progressive_passes_per_match": 40.37,
      "research_xt_created_per_match": 1.739,
      "shots_per_match": 12.03,
      "team": "Sassuolo",
      "team_id": 3315
    },
    {
      "chain_proxy_count": 13619,
      "chain_proxy_events": 32014,
      "goals_per_match": 1.39,
      "matches": 38,
      "pass_completion_pct": 83.1,
      "passes_attempted": 15919,
      "passes_completed": 13228,
      "progressive_chains_per_match": 91.84,
      "progressive_passes_per_match": 40.42,
      "research_xt_created_per_match": 1.788,
      "shots_per_match": 11.39,
      "team": "Torino",
      "team_id": 3185
    },
    {
      "chain_proxy_count": 13164,
      "chain_proxy_events": 30459,
      "goals_per_match": 1.18,
      "matches": 38,
      "pass_completion_pct": 81.3,
      "passes_attempted": 14525,
      "passes_completed": 11809,
      "progressive_chains_per_match": 97.24,
      "progressive_passes_per_match": 40.24,
      "research_xt_created_per_match": 1.752,
      "shots_per_match": 11.11,
      "team": "Udinese",
      "team_id": 3163
    }
  ]
}
